deepsport_utilities/__init__.py
deepsport_utilities/calib.py
deepsport_utilities/court.py
deepsport_utilities/dataset.py
deepsport_utilities/transforms.py
deepsport_utilities/utils.py
deepsport_utilities/dataset/__init__.py
deepsport_utilities/dataset/common.py
deepsport_utilities/dataset/legacy.py
deepsport_utilities/ds/__init__.py
deepsport_utilities/ds/generic_dataset.py
deepsport_utilities/ds/instants_dataset/__init__.py
deepsport_utilities/ds/instants_dataset/dataset_splitters.py
deepsport_utilities/ds/instants_dataset/instants_dataset.py
deepsport_utilities/ds/instants_dataset/instants_transforms.py
deepsport_utilities/ds/instants_dataset/mod_source.c
deepsport_utilities/ds/instants_dataset/views_dataset.py
deepsport_utilities/ds/instants_dataset/views_transforms.py
deepsport_utilities-5.2.0.dist-info/METADATA
deepsport_utilities-5.2.0.dist-info/WHEEL
deepsport_utilities-5.2.0.dist-info/RECORD
