Metadata-Version: 2.4
Name: deepsport_utilities
Version: 5.2.0
Project-URL: Homepage, https://gitlab.com/deepsport/deepsport_utilities
Author-email: Gabriel Van Zandycke <gabriel.vanzandycke@hotmail.com>
License: LGPL
Requires-Python: >=3.8.2
Requires-Dist: aleatorpy>=0.2.0
Requires-Dist: calib3d>=2.10.1
Requires-Dist: imageio>=2.9
Requires-Dist: m3u8>=6.0.0
Requires-Dist: mlworkflow>=0.6.0
Requires-Dist: numpy>=1.22
Requires-Dist: opencv-python>=4.10
Requires-Dist: requests>=2.0.0
Requires-Dist: scikit-image>=0.18
Requires-Dist: scipy>=1.10
Requires-Dist: shapely>=2.0.6
